{
    "zn":{
        "exchangeId":"SHFE",
        "include":[
            {
                "ticker":"zn2009",
                "name":"锌2009"
            },
            {
                "ticker":"zn2010",
                "name":"锌2010"
            },
            {
                "ticker":"zn2011",
                "name":"锌2011"
            },
            {
                "ticker":"zn2012",
                "name":"锌2012"
            },
            {
                "ticker":"zn2101",
                "name":"锌2101"
            },
            {
                "ticker":"zn2102",
                "name":"锌2102"
            },
            {
                "ticker":"zn2103",
                "name":"锌2103"
            },
            {
                "ticker":"zn2104",
                "name":"锌2104"
            },
            {
                "ticker":"zn2105",
                "name":"锌2105"
            },
            {
                "ticker":"zn2106",
                "name":"锌2106"
            },
            {
                "ticker":"zn2107",
                "name":"锌2107"
            },
            {
                "ticker":"zn2108",
                "name":"锌2108"
            }
        ]
    },
    "j":{
        "exchangeId":"DCE",
        "include":[
            {
                "ticker":"j2010",
                "name":"冶金焦炭2010"
            },
            {
                "ticker":"j2011",
                "name":"冶金焦炭2011"
            },
            {
                "ticker":"j2012",
                "name":"冶金焦炭2012"
            },
            {
                "ticker":"j2101",
                "name":"冶金焦炭2101"
            },
            {
                "ticker":"j2102",
                "name":"冶金焦炭2102"
            },
            {
                "ticker":"j2103",
                "name":"冶金焦炭2103"
            },
            {
                "ticker":"j2104",
                "name":"冶金焦炭2104"
            },
            {
                "ticker":"j2105",
                "name":"冶金焦炭2105"
            },
            {
                "ticker":"j2106",
                "name":"冶金焦炭2106"
            },
            {
                "ticker":"j2108",
                "name":"冶金焦炭2108"
            }
        ]
    },
    "ag":{
        "exchangeId":"SHFE",
        "include":[
            {
                "ticker":"ag2009",
                "name":"白银2009"
            },
            {
                "ticker":"ag2010",
                "name":"白银2010"
            },
            {
                "ticker":"ag2011",
                "name":"白银2011"
            },
            {
                "ticker":"ag2012",
                "name":"白银2012"
            },
            {
                "ticker":"ag2101",
                "name":"白银2101"
            },
            {
                "ticker":"ag2102",
                "name":"白银2102"
            },
            {
                "ticker":"ag2103",
                "name":"白银2103"
            },
            {
                "ticker":"ag2104",
                "name":"白银2104"
            },
            {
                "ticker":"ag2105",
                "name":"白银2105"
            },
            {
                "ticker":"ag2106",
                "name":"白银2106"
            },
            {
                "ticker":"ag2107",
                "name":"白银2107"
            },
            {
                "ticker":"ag2108",
                "name":"白银2108"
            }
        ]
    },
    "eg":{
        "exchangeId":"DCE",
        "include":[
            {
                "ticker":"eg2009",
                "name":"乙二醇2009"
            },
            {
                "ticker":"eg2010",
                "name":"乙二醇2010"
            },
            {
                "ticker":"eg2011",
                "name":"乙二醇2011"
            },
            {
                "ticker":"eg2012",
                "name":"乙二醇2012"
            },
            {
                "ticker":"eg2101",
                "name":"乙二醇2101"
            },
            {
                "ticker":"eg2102",
                "name":"乙二醇2102"
            },
            {
                "ticker":"eg2103",
                "name":"乙二醇2103"
            },
            {
                "ticker":"eg2104",
                "name":"乙二醇2104"
            },
            {
                "ticker":"eg2105",
                "name":"乙二醇2105"
            },
            {
                "ticker":"eg2106",
                "name":"乙二醇2106"
            },
            {
                "ticker":"eg2107",
                "name":"乙二醇2107"
            },
            {
                "ticker":"eg2108",
                "name":"乙二醇2108"
            }
        ]
    },
    "al":{
        "exchangeId":"SHFE",
        "include":[
            {
                "ticker":"al2009",
                "name":"铝2009"
            },
            {
                "ticker":"al2010",
                "name":"铝2010"
            },
            {
                "ticker":"al2011",
                "name":"铝2011"
            },
            {
                "ticker":"al2012",
                "name":"铝2012"
            },
            {
                "ticker":"al2101",
                "name":"铝2101"
            },
            {
                "ticker":"al2102",
                "name":"铝2102"
            },
            {
                "ticker":"al2103",
                "name":"铝2103"
            },
            {
                "ticker":"al2104",
                "name":"铝2104"
            },
            {
                "ticker":"al2105",
                "name":"铝2105"
            },
            {
                "ticker":"al2106",
                "name":"铝2106"
            },
            {
                "ticker":"al2107",
                "name":"铝2107"
            },
            {
                "ticker":"al2108",
                "name":"铝2108"
            }
        ]
    },
    "JR":{
        "exchangeId":"CZCE",
        "include":[
            {
                "ticker":"JR011",
                "name":"粳稻011"
            },
            {
                "ticker":"JR101",
                "name":"粳稻101"
            },
            {
                "ticker":"JR105",
                "name":"粳稻105"
            }
        ]
    },
    "eb":{
        "exchangeId":"DCE",
        "include":[
            {
                "ticker":"eb2009",
                "name":"苯乙烯2009"
            },
            {
                "ticker":"eb2010",
                "name":"苯乙烯2010"
            },
            {
                "ticker":"eb2011",
                "name":"苯乙烯2011"
            },
            {
                "ticker":"eb2012",
                "name":"苯乙烯2012"
            },
            {
                "ticker":"eb2101",
                "name":"苯乙烯2101"
            },
            {
                "ticker":"eb2102",
                "name":"苯乙烯2102"
            },
            {
                "ticker":"eb2103",
                "name":"苯乙烯2103"
            },
            {
                "ticker":"eb2104",
                "name":"苯乙烯2104"
            },
            {
                "ticker":"eb2105",
                "name":"苯乙烯2105"
            },
            {
                "ticker":"eb2106",
                "name":"苯乙烯2106"
            },
            {
                "ticker":"eb2107",
                "name":"苯乙烯2107"
            },
            {
                "ticker":"eb2108",
                "name":"苯乙烯2108"
            }
        ]
    },
    "MAMA":{
        "exchangeId":"CZCE",
        "include":[
            {
                "ticker":"MA010",
                "name":"甲醇MA010"
            },
            {
                "ticker":"MA011",
                "name":"甲醇MA011"
            },
            {
                "ticker":"MA012",
                "name":"甲醇MA012"
            },
            {
                "ticker":"MA101",
                "name":"甲醇MA101"
            },
            {
                "ticker":"MA102",
                "name":"甲醇MA102"
            },
            {
                "ticker":"MA103",
                "name":"甲醇MA103"
            },
            {
                "ticker":"MA104",
                "name":"甲醇MA104"
            },
            {
                "ticker":"MA105",
                "name":"甲醇MA105"
            },
            {
                "ticker":"MA106",
                "name":"甲醇MA106"
            },
            {
                "ticker":"MA107",
                "name":"甲醇MA107"
            },
            {
                "ticker":"MA108",
                "name":"甲醇MA108"
            }
        ]
    },
    "au":{
        "exchangeId":"SHFE",
        "include":[
            {
                "ticker":"au2010",
                "name":"黄金2010"
            },
            {
                "ticker":"au2012",
                "name":"黄金2012"
            },
            {
                "ticker":"au2102",
                "name":"黄金2102"
            },
            {
                "ticker":"au2104",
                "name":"黄金2104"
            },
            {
                "ticker":"au2106",
                "name":"黄金2106"
            },
            {
                "ticker":"au2009",
                "name":"黄金2009"
            },
            {
                "ticker":"au2108",
                "name":"黄金2108"
            },
            {
                "ticker":"au2011",
                "name":"黄金2011"
            }
        ]
    },
    "FG":{
        "exchangeId":"CZCE",
        "include":[
            {
                "ticker":"FG010",
                "name":"玻璃010"
            },
            {
                "ticker":"FG011",
                "name":"玻璃011"
            },
            {
                "ticker":"FG012",
                "name":"玻璃012"
            },
            {
                "ticker":"FG101",
                "name":"玻璃101"
            },
            {
                "ticker":"FG102",
                "name":"玻璃102"
            },
            {
                "ticker":"FG103",
                "name":"玻璃103"
            },
            {
                "ticker":"FG104",
                "name":"玻璃104"
            },
            {
                "ticker":"FG105",
                "name":"玻璃105"
            },
            {
                "ticker":"FG106",
                "name":"玻璃106"
            },
            {
                "ticker":"FG107",
                "name":"玻璃107"
            },
            {
                "ticker":"FG108",
                "name":"玻璃108"
            }
        ]
    },
    "cs":{
        "exchangeId":"DCE",
        "include":[
            {
                "ticker":"cs2011",
                "name":"玉米淀粉2011"
            },
            {
                "ticker":"cs2101",
                "name":"玉米淀粉2101"
            },
            {
                "ticker":"cs2103",
                "name":"玉米淀粉2103"
            },
            {
                "ticker":"cs2105",
                "name":"玉米淀粉2105"
            },
            {
                "ticker":"cs2107",
                "name":"玉米淀粉2107"
            }
        ]
    },
    "cu":{
        "exchangeId":"SHFE",
        "include":[
            {
                "ticker":"cu2009",
                "name":"铜2009"
            },
            {
                "ticker":"cu2010",
                "name":"铜2010"
            },
            {
                "ticker":"cu2011",
                "name":"铜2011"
            },
            {
                "ticker":"cu2012",
                "name":"铜2012"
            },
            {
                "ticker":"cu2101",
                "name":"铜2101"
            },
            {
                "ticker":"cu2102",
                "name":"铜2102"
            },
            {
                "ticker":"cu2103",
                "name":"铜2103"
            },
            {
                "ticker":"cu2104",
                "name":"铜2104"
            },
            {
                "ticker":"cu2105",
                "name":"铜2105"
            },
            {
                "ticker":"cu2106",
                "name":"铜2106"
            },
            {
                "ticker":"cu2107",
                "name":"铜2107"
            },
            {
                "ticker":"cu2108",
                "name":"铜2108"
            }
        ]
    },
    "ni":{
        "exchangeId":"SHFE",
        "include":[
            {
                "ticker":"ni2009",
                "name":"镍2009"
            },
            {
                "ticker":"ni2010",
                "name":"镍2010"
            },
            {
                "ticker":"ni2011",
                "name":"镍2011"
            },
            {
                "ticker":"ni2012",
                "name":"镍2012"
            },
            {
                "ticker":"ni2101",
                "name":"镍2101"
            },
            {
                "ticker":"ni2102",
                "name":"镍2102"
            },
            {
                "ticker":"ni2103",
                "name":"镍2103"
            },
            {
                "ticker":"ni2104",
                "name":"镍2104"
            },
            {
                "ticker":"ni2105",
                "name":"镍2105"
            },
            {
                "ticker":"ni2106",
                "name":"镍2106"
            },
            {
                "ticker":"ni2107",
                "name":"镍2107"
            },
            {
                "ticker":"ni2108",
                "name":"镍2108"
            }
        ]
    },
    "pp":{
        "exchangeId":"DCE",
        "include":[
            {
                "ticker":"pp2010",
                "name":"聚丙烯2010"
            },
            {
                "ticker":"pp2011",
                "name":"聚丙烯2011"
            },
            {
                "ticker":"pp2012",
                "name":"聚丙烯2012"
            },
            {
                "ticker":"pp2101",
                "name":"聚丙烯2101"
            },
            {
                "ticker":"pp2102",
                "name":"聚丙烯2102"
            },
            {
                "ticker":"pp2103",
                "name":"聚丙烯2103"
            },
            {
                "ticker":"pp2104",
                "name":"聚丙烯2104"
            },
            {
                "ticker":"pp2105",
                "name":"聚丙烯2105"
            },
            {
                "ticker":"pp2106",
                "name":"聚丙烯2106"
            },
            {
                "ticker":"pp2107",
                "name":"聚丙烯2107"
            },
            {
                "ticker":"pp2108",
                "name":"聚丙烯2108"
            }
        ]
    },
    "rr":{
        "exchangeId":"DCE",
        "include":[
            {
                "ticker":"rr2010",
                "name":"粳米2010"
            },
            {
                "ticker":"rr2011",
                "name":"粳米2011"
            },
            {
                "ticker":"rr2012",
                "name":"粳米2012"
            },
            {
                "ticker":"rr2101",
                "name":"粳米2101"
            },
            {
                "ticker":"rr2102",
                "name":"粳米2102"
            },
            {
                "ticker":"rr2103",
                "name":"粳米2103"
            },
            {
                "ticker":"rr2104",
                "name":"粳米2104"
            },
            {
                "ticker":"rr2105",
                "name":"粳米2105"
            },
            {
                "ticker":"rr2106",
                "name":"粳米2106"
            },
            {
                "ticker":"rr2107",
                "name":"粳米2107"
            },
            {
                "ticker":"rr2108",
                "name":"粳米2108"
            }
        ]
    },
    "p":{
        "exchangeId":"DCE",
        "include":[
            {
                "ticker":"p2010",
                "name":"棕榈油2010"
            },
            {
                "ticker":"p2011",
                "name":"棕榈油2011"
            },
            {
                "ticker":"p2012",
                "name":"棕榈油2012"
            },
            {
                "ticker":"p2101",
                "name":"棕榈油2101"
            },
            {
                "ticker":"p2102",
                "name":"棕榈油2102"
            },
            {
                "ticker":"p2103",
                "name":"棕榈油2103"
            },
            {
                "ticker":"p2104",
                "name":"棕榈油2104"
            },
            {
                "ticker":"p2105",
                "name":"棕榈油2105"
            },
            {
                "ticker":"p2106",
                "name":"棕榈油2106"
            },
            {
                "ticker":"p2107",
                "name":"棕榈油2107"
            }
        ]
    },
    "TS":{
        "exchangeId":"CFFEX",
        "include":[
            {
                "ticker":"TS2012",
                "name":"2年期国债2012"
            },
            {
                "ticker":"TS2103",
                "name":"2年期国债2103"
            },
            {
                "ticker":"TS2106",
                "name":"2年期国债2106"
            }
        ]
    },
    "pb":{
        "exchangeId":"SHFE",
        "include":[
            {
                "ticker":"pb2009",
                "name":"铅2009"
            },
            {
                "ticker":"pb2010",
                "name":"铅2010"
            },
            {
                "ticker":"pb2011",
                "name":"铅2011"
            },
            {
                "ticker":"pb2012",
                "name":"铅2012"
            },
            {
                "ticker":"pb2101",
                "name":"铅2101"
            },
            {
                "ticker":"pb2102",
                "name":"铅2102"
            },
            {
                "ticker":"pb2103",
                "name":"铅2103"
            },
            {
                "ticker":"pb2104",
                "name":"铅2104"
            },
            {
                "ticker":"pb2105",
                "name":"铅2105"
            },
            {
                "ticker":"pb2106",
                "name":"铅2106"
            },
            {
                "ticker":"pb2107",
                "name":"铅2107"
            },
            {
                "ticker":"pb2108",
                "name":"铅2108"
            }
        ]
    },
    "lu":{
        "exchangeId":"INE",
        "include":[
            {
                "ticker":"lu2103",
                "name":"低硫燃料油2103"
            },
            {
                "ticker":"lu2105",
                "name":"低硫燃料油2105"
            },
            {
                "ticker":"lu2101",
                "name":"低硫燃料油2101"
            },
            {
                "ticker":"lu2102",
                "name":"低硫燃料油2102"
            },
            {
                "ticker":"lu2106",
                "name":"低硫燃料油2106"
            },
            {
                "ticker":"lu2104",
                "name":"低硫燃料油2104"
            },
            {
                "ticker":"lu2107",
                "name":"低硫燃料油2107"
            },
            {
                "ticker":"lu2108",
                "name":"低硫燃料油2108"
            },
            {
                "ticker":"lu2109",
                "name":"低硫燃料油2109"
            }
        ]
    },
    "LR":{
        "exchangeId":"CZCE",
        "include":[
            {
                "ticker":"LR011",
                "name":"晚籼稻011"
            }
        ]
    },
    "pg":{
        "exchangeId":"DCE",
        "include":[
            {
                "ticker":"pg2103",
                "name":"液化石油气2103"
            },
            {
                "ticker":"pg2011",
                "name":"液化石油气2011"
            },
            {
                "ticker":"pg2101",
                "name":"液化石油气2101"
            },
            {
                "ticker":"pg2012",
                "name":"液化石油气2012"
            },
            {
                "ticker":"pg2102",
                "name":"液化石油气2102"
            },
            {
                "ticker":"pg2104",
                "name":"液化石油气2104"
            },
            {
                "ticker":"pg2105",
                "name":"液化石油气2105"
            },
            {
                "ticker":"pg2106",
                "name":"液化石油气2106"
            },
            {
                "ticker":"pg2107",
                "name":"液化石油气2107"
            },
            {
                "ticker":"pg2108",
                "name":"液化石油气2108"
            }
        ]
    },
    "rb":{
        "exchangeId":"SHFE",
        "include":[
            {
                "ticker":"rb2009",
                "name":"螺纹钢2009"
            },
            {
                "ticker":"rb2010",
                "name":"螺纹钢2010"
            },
            {
                "ticker":"rb2011",
                "name":"螺纹钢2011"
            },
            {
                "ticker":"rb2012",
                "name":"螺纹钢2012"
            },
            {
                "ticker":"rb2101",
                "name":"螺纹钢2101"
            },
            {
                "ticker":"rb2102",
                "name":"螺纹钢2102"
            },
            {
                "ticker":"rb2103",
                "name":"螺纹钢2103"
            },
            {
                "ticker":"rb2104",
                "name":"螺纹钢2104"
            },
            {
                "ticker":"rb2105",
                "name":"螺纹钢2105"
            },
            {
                "ticker":"rb2106",
                "name":"螺纹钢2106"
            },
            {
                "ticker":"rb2107",
                "name":"螺纹钢2107"
            },
            {
                "ticker":"rb2108",
                "name":"螺纹钢2108"
            }
        ]
    },
    "TF":{
        "exchangeId":"CFFEX",
        "include":[
            {
                "ticker":"TF2012",
                "name":"5年期国债2012"
            },
            {
                "ticker":"TF2103",
                "name":"5年期国债2103"
            },
            {
                "ticker":"TF2106",
                "name":"5年期国债2106"
            }
        ]
    },
    "RM":{
        "exchangeId":"CZCE",
        "include":[
            {
                "ticker":"RM011",
                "name":"菜籽粕011"
            },
            {
                "ticker":"RM101",
                "name":"菜籽粕101"
            },
            {
                "ticker":"RM103",
                "name":"菜籽粕103"
            },
            {
                "ticker":"RM105",
                "name":"菜籽粕105"
            },
            {
                "ticker":"RM107",
                "name":"菜籽粕107"
            },
            {
                "ticker":"RM108",
                "name":"菜籽粕108"
            }
        ]
    },
    "nr":{
        "exchangeId":"INE",
        "include":[
            {
                "ticker":"nr2009",
                "name":"20号胶2009"
            },
            {
                "ticker":"nr2010",
                "name":"20号胶2010"
            },
            {
                "ticker":"nr2011",
                "name":"20号胶2011"
            },
            {
                "ticker":"nr2012",
                "name":"20号胶2012"
            },
            {
                "ticker":"nr2101",
                "name":"20号胶2101"
            },
            {
                "ticker":"nr2102",
                "name":"20号胶2102"
            },
            {
                "ticker":"nr2103",
                "name":"20号胶2103"
            },
            {
                "ticker":"nr2105",
                "name":"20号胶2105"
            }
        ]
    },
    "PM":{
        "exchangeId":"CZCE",
        "include":[
            {
                "ticker":"PM103",
                "name":"普通小麦103"
            },
            {
                "ticker":"PM105",
                "name":"普通小麦105"
            }
        ]
    },
    "CJ":{
        "exchangeId":"CZCE",
        "include":[
            {
                "ticker":"CJ012",
                "name":"红枣012"
            },
            {
                "ticker":"CJ101",
                "name":"红枣101"
            },
            {
                "ticker":"CJ103",
                "name":"红枣103"
            },
            {
                "ticker":"CJ105",
                "name":"红枣105"
            },
            {
                "ticker":"CJ107",
                "name":"红枣107"
            }
        ]
    },
    "AP":{
        "exchangeId":"CZCE",
        "include":[
            {
                "ticker":"AP010",
                "name":"鲜苹果010"
            },
            {
                "ticker":"AP011",
                "name":"鲜苹果011"
            },
            {
                "ticker":"AP012",
                "name":"鲜苹果012"
            },
            {
                "ticker":"AP101",
                "name":"鲜苹果101"
            },
            {
                "ticker":"AP103",
                "name":"鲜苹果103"
            },
            {
                "ticker":"AP105",
                "name":"鲜苹果105"
            }
        ]
    },
    "fu":{
        "exchangeId":"SHFE",
        "include":[
            {
                "ticker":"fu2010",
                "name":"燃料油2010"
            },
            {
                "ticker":"fu2011",
                "name":"燃料油2011"
            },
            {
                "ticker":"fu2012",
                "name":"燃料油2012"
            },
            {
                "ticker":"fu2101",
                "name":"燃料油2101"
            },
            {
                "ticker":"fu2102",
                "name":"燃料油2102"
            },
            {
                "ticker":"fu2103",
                "name":"燃料油2103"
            },
            {
                "ticker":"fu2104",
                "name":"燃料油2104"
            },
            {
                "ticker":"fu2105",
                "name":"燃料油2105"
            },
            {
                "ticker":"fu2106",
                "name":"燃料油2106"
            },
            {
                "ticker":"fu2107",
                "name":"燃料油2107"
            },
            {
                "ticker":"fu2108",
                "name":"燃料油2108"
            },
            {
                "ticker":"fu2109",
                "name":"燃料油2109"
            }
        ]
    },
    "ru":{
        "exchangeId":"SHFE",
        "include":[
            {
                "ticker":"ru2009",
                "name":"天然橡胶2009"
            },
            {
                "ticker":"ru2010",
                "name":"天然橡胶2010"
            },
            {
                "ticker":"ru2011",
                "name":"天然橡胶2011"
            },
            {
                "ticker":"ru2101",
                "name":"天然橡胶2101"
            },
            {
                "ticker":"ru2103",
                "name":"天然橡胶2103"
            },
            {
                "ticker":"ru2104",
                "name":"天然橡胶2104"
            },
            {
                "ticker":"ru2105",
                "name":"天然橡胶2105"
            },
            {
                "ticker":"ru2106",
                "name":"天然橡胶2106"
            },
            {
                "ticker":"ru2107",
                "name":"天然橡胶2107"
            },
            {
                "ticker":"ru2108",
                "name":"天然橡胶2108"
            }
        ]
    },
    "CY":{
        "exchangeId":"CZCE",
        "include":[
            {
                "ticker":"CY101",
                "name":"棉纱101"
            },
            {
                "ticker":"CY104",
                "name":"棉纱104"
            },
            {
                "ticker":"CY105",
                "name":"棉纱105"
            }
        ]
    },
    "CF":{
        "exchangeId":"CZCE",
        "include":[
            {
                "ticker":"CF011",
                "name":"一号棉花011"
            },
            {
                "ticker":"CF101",
                "name":"一号棉花101"
            },
            {
                "ticker":"CF103",
                "name":"一号棉花103"
            },
            {
                "ticker":"CF105",
                "name":"一号棉花105"
            },
            {
                "ticker":"CF107",
                "name":"一号棉花107"
            }
        ]
    },
    "bu":{
        "exchangeId":"SHFE",
        "include":[
            {
                "ticker":"bu2009",
                "name":"石油沥青2009"
            },
            {
                "ticker":"bu2012",
                "name":"石油沥青2012"
            },
            {
                "ticker":"bu2103",
                "name":"石油沥青2103"
            },
            {
                "ticker":"bu2106",
                "name":"石油沥青2106"
            },
            {
                "ticker":"bu2109",
                "name":"石油沥青2109"
            },
            {
                "ticker":"bu2112",
                "name":"石油沥青2112"
            },
            {
                "ticker":"bu2203",
                "name":"石油沥青2203"
            },
            {
                "ticker":"bu2010",
                "name":"石油沥青2010"
            },
            {
                "ticker":"bu2011",
                "name":"石油沥青2011"
            },
            {
                "ticker":"bu2206",
                "name":"石油沥青2206"
            },
            {
                "ticker":"bu2101",
                "name":"石油沥青2101"
            },
            {
                "ticker":"bu2102",
                "name":"石油沥青2102"
            }
        ]
    },
    "fb":{
        "exchangeId":"DCE",
        "include":[
            {
                "ticker":"fb2010",
                "name":"纤维板2010"
            },
            {
                "ticker":"fb2011",
                "name":"纤维板2011"
            },
            {
                "ticker":"fb2101",
                "name":"纤维板2101"
            }
        ]
    },
    "wr":{
        "exchangeId":"SHFE",
        "include":[
            {
                "ticker":"wr2009",
                "name":"线材2009"
            },
            {
                "ticker":"wr2010",
                "name":"线材2010"
            },
            {
                "ticker":"wr2011",
                "name":"线材2011"
            },
            {
                "ticker":"wr2012",
                "name":"线材2012"
            },
            {
                "ticker":"wr2101",
                "name":"线材2101"
            },
            {
                "ticker":"wr2102",
                "name":"线材2102"
            },
            {
                "ticker":"wr2103",
                "name":"线材2103"
            },
            {
                "ticker":"wr2105",
                "name":"线材2105"
            },
            {
                "ticker":"wr2106",
                "name":"线材2106"
            },
            {
                "ticker":"wr2107",
                "name":"线材2107"
            },
            {
                "ticker":"wr2108",
                "name":"线材2108"
            }
        ]
    },
    "jd":{
        "exchangeId":"DCE",
        "include":[
            {
                "ticker":"jd2009",
                "name":"鲜鸡蛋2009"
            },
            {
                "ticker":"jd2010",
                "name":"鲜鸡蛋2010"
            },
            {
                "ticker":"jd2011",
                "name":"鲜鸡蛋2011"
            },
            {
                "ticker":"jd2012",
                "name":"鲜鸡蛋2012"
            },
            {
                "ticker":"jd2101",
                "name":"鲜鸡蛋2101"
            },
            {
                "ticker":"jd2102",
                "name":"鲜鸡蛋2102"
            },
            {
                "ticker":"jd2103",
                "name":"鲜鸡蛋2103"
            },
            {
                "ticker":"jd2104",
                "name":"鲜鸡蛋2104"
            },
            {
                "ticker":"jd2105",
                "name":"鲜鸡蛋2105"
            },
            {
                "ticker":"jd2106",
                "name":"鲜鸡蛋2106"
            },
            {
                "ticker":"jd2107",
                "name":"鲜鸡蛋2107"
            },
            {
                "ticker":"jd2108",
                "name":"鲜鸡蛋2108"
            }
        ]
    },
    "hc":{
        "exchangeId":"SHFE",
        "include":[
            {
                "ticker":"hc2009",
                "name":"热轧卷板2009"
            },
            {
                "ticker":"hc2010",
                "name":"热轧卷板2010"
            },
            {
                "ticker":"hc2011",
                "name":"热轧卷板2011"
            },
            {
                "ticker":"hc2012",
                "name":"热轧卷板2012"
            },
            {
                "ticker":"hc2101",
                "name":"热轧卷板2101"
            },
            {
                "ticker":"hc2102",
                "name":"热轧卷板2102"
            },
            {
                "ticker":"hc2103",
                "name":"热轧卷板2103"
            },
            {
                "ticker":"hc2104",
                "name":"热轧卷板2104"
            },
            {
                "ticker":"hc2105",
                "name":"热轧卷板2105"
            },
            {
                "ticker":"hc2106",
                "name":"热轧卷板2106"
            }
        ]
    },
    "IC":{
        "exchangeId":"CFFEX",
        "include":[
            {
                "ticker":"IC2009",
                "name":"中证500指数2009"
            },
            {
                "ticker":"IC2012",
                "name":"中证500指数2012"
            },
            {
                "ticker":"IC2103",
                "name":"中证500指数2103"
            },
            {
                "ticker":"IC2010",
                "name":"中证500指数2010"
            }
        ]
    },
    "WH":{
        "exchangeId":"CZCE",
        "include":[
            {
                "ticker":"WH011",
                "name":"优质强筋小麦011"
            },
            {
                "ticker":"WH101",
                "name":"优质强筋小麦101"
            },
            {
                "ticker":"WH103",
                "name":"优质强筋小麦103"
            },
            {
                "ticker":"WH105",
                "name":"优质强筋小麦105"
            }
        ]
    },
    "SR":{
        "exchangeId":"CZCE",
        "include":[
            {
                "ticker":"SR011",
                "name":"白砂糖011"
            },
            {
                "ticker":"SR101",
                "name":"白砂糖101"
            },
            {
                "ticker":"SR103",
                "name":"白砂糖103"
            },
            {
                "ticker":"SR105",
                "name":"白砂糖105"
            },
            {
                "ticker":"SR107",
                "name":"白砂糖107"
            }
        ]
    },
    "a":{
        "exchangeId":"DCE",
        "include":[
            {
                "ticker":"a2011",
                "name":"黄大豆1号2011"
            },
            {
                "ticker":"a2101",
                "name":"黄大豆1号2101"
            },
            {
                "ticker":"a2103",
                "name":"黄大豆1号2103"
            },
            {
                "ticker":"a2105",
                "name":"黄大豆1号2105"
            },
            {
                "ticker":"a2107",
                "name":"黄大豆1号2107"
            }
        ]
    },
    "c":{
        "exchangeId":"DCE",
        "include":[
            {
                "ticker":"c2011",
                "name":"黄玉米2011"
            },
            {
                "ticker":"c2101",
                "name":"黄玉米2101"
            },
            {
                "ticker":"c2103",
                "name":"黄玉米2103"
            },
            {
                "ticker":"c2105",
                "name":"黄玉米2105"
            },
            {
                "ticker":"c2107",
                "name":"黄玉米2107"
            }
        ]
    },
    "b":{
        "exchangeId":"DCE",
        "include":[
            {
                "ticker":"b2010",
                "name":"黄大豆2号2010"
            },
            {
                "ticker":"b2011",
                "name":"黄大豆2号2011"
            },
            {
                "ticker":"b2012",
                "name":"黄大豆2号2012"
            },
            {
                "ticker":"b2101",
                "name":"黄大豆2号2101"
            },
            {
                "ticker":"b2102",
                "name":"黄大豆2号2102"
            },
            {
                "ticker":"b2103",
                "name":"黄大豆2号2103"
            },
            {
                "ticker":"b2104",
                "name":"黄大豆2号2104"
            },
            {
                "ticker":"b2105",
                "name":"黄大豆2号2105"
            },
            {
                "ticker":"b2106",
                "name":"黄大豆2号2106"
            },
            {
                "ticker":"b2107",
                "name":"黄大豆2号2107"
            },
            {
                "ticker":"b2108",
                "name":"黄大豆2号2108"
            }
        ]
    },
    "sc":{
        "exchangeId":"INE",
        "include":[
            {
                "ticker":"sc2012",
                "name":"原油2012"
            },
            {
                "ticker":"sc2103",
                "name":"原油2103"
            },
            {
                "ticker":"sc2106",
                "name":"原油2106"
            },
            {
                "ticker":"sc2109",
                "name":"原油2109"
            },
            {
                "ticker":"sc2112",
                "name":"原油2112"
            },
            {
                "ticker":"sc2203",
                "name":"原油2203"
            },
            {
                "ticker":"sc2206",
                "name":"原油2206"
            },
            {
                "ticker":"sc2209",
                "name":"原油2209"
            },
            {
                "ticker":"sc2010",
                "name":"原油2010"
            },
            {
                "ticker":"sc2011",
                "name":"原油2011"
            },
            {
                "ticker":"sc2212",
                "name":"原油2212"
            },
            {
                "ticker":"sc2101",
                "name":"原油2101"
            },
            {
                "ticker":"sc2102",
                "name":"原油2102"
            },
            {
                "ticker":"sc2303",
                "name":"原油2303"
            },
            {
                "ticker":"sc2104",
                "name":"原油2104"
            },
            {
                "ticker":"sc2105",
                "name":"原油2105"
            },
            {
                "ticker":"sc2306",
                "name":"原油2306"
            },
            {
                "ticker":"sc2107",
                "name":"原油2107"
            },
            {
                "ticker":"sc2108",
                "name":"原油2108"
            },
            {
                "ticker":"sc2309",
                "name":"原油2309"
            }
        ]
    },
    "OI":{
        "exchangeId":"CZCE",
        "include":[
            {
                "ticker":"OI011",
                "name":"菜籽油011"
            },
            {
                "ticker":"OI101",
                "name":"菜籽油101"
            },
            {
                "ticker":"OI103",
                "name":"菜籽油103"
            },
            {
                "ticker":"OI105",
                "name":"菜籽油105"
            },
            {
                "ticker":"OI107",
                "name":"菜籽油107"
            }
        ]
    },
    "jm":{
        "exchangeId":"DCE",
        "include":[
            {
                "ticker":"jm2010",
                "name":"焦煤2010"
            },
            {
                "ticker":"jm2011",
                "name":"焦煤2011"
            },
            {
                "ticker":"jm2012",
                "name":"焦煤2012"
            },
            {
                "ticker":"jm2101",
                "name":"焦煤2101"
            },
            {
                "ticker":"jm2102",
                "name":"焦煤2102"
            },
            {
                "ticker":"jm2103",
                "name":"焦煤2103"
            },
            {
                "ticker":"jm2104",
                "name":"焦煤2104"
            },
            {
                "ticker":"jm2105",
                "name":"焦煤2105"
            }
        ]
    },
    "ss":{
        "exchangeId":"SHFE",
        "include":[
            {
                "ticker":"ss2009",
                "name":"不锈钢2009"
            },
            {
                "ticker":"ss2010",
                "name":"不锈钢2010"
            },
            {
                "ticker":"ss2011",
                "name":"不锈钢2011"
            },
            {
                "ticker":"ss2012",
                "name":"不锈钢2012"
            },
            {
                "ticker":"ss2101",
                "name":"不锈钢2101"
            },
            {
                "ticker":"ss2102",
                "name":"不锈钢2102"
            },
            {
                "ticker":"ss2103",
                "name":"不锈钢2103"
            },
            {
                "ticker":"ss2104",
                "name":"不锈钢2104"
            },
            {
                "ticker":"ss2105",
                "name":"不锈钢2105"
            },
            {
                "ticker":"ss2106",
                "name":"不锈钢2106"
            },
            {
                "ticker":"ss2107",
                "name":"不锈钢2107"
            },
            {
                "ticker":"ss2108",
                "name":"不锈钢2108"
            }
        ]
    },
    "RS":{
        "exchangeId":"CZCE",
        "include":[
            {
                "ticker":"RS011",
                "name":"油菜籽011"
            }
        ]
    },
    "sp":{
        "exchangeId":"SHFE",
        "include":[
            {
                "ticker":"sp2009",
                "name":"漂针浆2009"
            },
            {
                "ticker":"sp2010",
                "name":"漂针浆2010"
            },
            {
                "ticker":"sp2011",
                "name":"漂针浆2011"
            },
            {
                "ticker":"sp2012",
                "name":"漂针浆2012"
            },
            {
                "ticker":"sp2101",
                "name":"漂针浆2101"
            },
            {
                "ticker":"sp2102",
                "name":"漂针浆2102"
            },
            {
                "ticker":"sp2103",
                "name":"漂针浆2103"
            },
            {
                "ticker":"sp2104",
                "name":"漂针浆2104"
            },
            {
                "ticker":"sp2105",
                "name":"漂针浆2105"
            },
            {
                "ticker":"sp2106",
                "name":"漂针浆2106"
            },
            {
                "ticker":"sp2107",
                "name":"漂针浆2107"
            },
            {
                "ticker":"sp2108",
                "name":"漂针浆2108"
            }
        ]
    },
    "m":{
        "exchangeId":"DCE",
        "include":[
            {
                "ticker":"m2011",
                "name":"豆粕2011"
            },
            {
                "ticker":"m2012",
                "name":"豆粕2012"
            },
            {
                "ticker":"m2101",
                "name":"豆粕2101"
            },
            {
                "ticker":"m2103",
                "name":"豆粕2103"
            },
            {
                "ticker":"m2105",
                "name":"豆粕2105"
            },
            {
                "ticker":"m2107",
                "name":"豆粕2107"
            },
            {
                "ticker":"m2108",
                "name":"豆粕2108"
            }
        ]
    },
    "l":{
        "exchangeId":"DCE",
        "include":[
            {
                "ticker":"l2010",
                "name":"线型低密度聚乙烯2010"
            },
            {
                "ticker":"l2011",
                "name":"线型低密度聚乙烯2011"
            },
            {
                "ticker":"l2012",
                "name":"线型低密度聚乙烯2012"
            },
            {
                "ticker":"l2101",
                "name":"线型低密度聚乙烯2101"
            },
            {
                "ticker":"l2102",
                "name":"线型低密度聚乙烯2102"
            },
            {
                "ticker":"l2103",
                "name":"线型低密度聚乙烯2103"
            },
            {
                "ticker":"l2104",
                "name":"线型低密度聚乙烯2104"
            },
            {
                "ticker":"l2105",
                "name":"线型低密度聚乙烯2105"
            },
            {
                "ticker":"l2106",
                "name":"线型低密度聚乙烯2106"
            },
            {
                "ticker":"l2107",
                "name":"线型低密度聚乙烯2107"
            },
            {
                "ticker":"l2108",
                "name":"线型低密度聚乙烯2108"
            }
        ]
    },
    "IFIF":{
        "exchangeId":"CFFEX",
        "include":[
            {
                "ticker":"IF2009",
                "name":"IF2009"
            },
            {
                "ticker":"IF2012",
                "name":"IF2012"
            },
            {
                "ticker":"IF2103",
                "name":"IF2103"
            },
            {
                "ticker":"IF2010",
                "name":"IF2010"
            }
        ]
    },
    "UR":{
        "exchangeId":"CZCE",
        "include":[
            {
                "ticker":"UR010",
                "name":"尿素010"
            },
            {
                "ticker":"UR011",
                "name":"尿素011"
            },
            {
                "ticker":"UR012",
                "name":"尿素012"
            },
            {
                "ticker":"UR101",
                "name":"尿素101"
            },
            {
                "ticker":"UR102",
                "name":"尿素102"
            },
            {
                "ticker":"UR103",
                "name":"尿素103"
            },
            {
                "ticker":"UR104",
                "name":"尿素104"
            },
            {
                "ticker":"UR105",
                "name":"尿素105"
            },
            {
                "ticker":"UR106",
                "name":"尿素106"
            },
            {
                "ticker":"UR107",
                "name":"尿素107"
            }
        ]
    },
    "ZCZC":{
        "exchangeId":"CZCE",
        "include":[
            {
                "ticker":"ZC010",
                "name":"动力煤ZC010"
            },
            {
                "ticker":"ZC011",
                "name":"动力煤ZC011"
            },
            {
                "ticker":"ZC012",
                "name":"动力煤ZC012"
            },
            {
                "ticker":"ZC101",
                "name":"动力煤ZC101"
            },
            {
                "ticker":"ZC102",
                "name":"动力煤ZC102"
            },
            {
                "ticker":"ZC103",
                "name":"动力煤ZC103"
            },
            {
                "ticker":"ZC105",
                "name":"动力煤ZC105"
            },
            {
                "ticker":"ZC107",
                "name":"动力煤ZC107"
            },
            {
                "ticker":"ZC109",
                "name":"动力煤ZC109"
            }
        ]
    },
    "i":{
        "exchangeId":"DCE",
        "include":[
            {
                "ticker":"i2010",
                "name":"铁矿石2010"
            },
            {
                "ticker":"i2011",
                "name":"铁矿石2011"
            },
            {
                "ticker":"i2012",
                "name":"铁矿石2012"
            },
            {
                "ticker":"i2101",
                "name":"铁矿石2101"
            },
            {
                "ticker":"i2102",
                "name":"铁矿石2102"
            },
            {
                "ticker":"i2103",
                "name":"铁矿石2103"
            },
            {
                "ticker":"i2104",
                "name":"铁矿石2104"
            },
            {
                "ticker":"i2105",
                "name":"铁矿石2105"
            },
            {
                "ticker":"i2106",
                "name":"铁矿石2106"
            },
            {
                "ticker":"i2107",
                "name":"铁矿石2107"
            },
            {
                "ticker":"i2108",
                "name":"铁矿石2108"
            }
        ]
    },
    "IH":{
        "exchangeId":"CFFEX",
        "include":[
            {
                "ticker":"IH2009",
                "name":"上证50指数2009"
            },
            {
                "ticker":"IH2012",
                "name":"上证50指数2012"
            },
            {
                "ticker":"IH2103",
                "name":"上证50指数2103"
            },
            {
                "ticker":"IH2010",
                "name":"上证50指数2010"
            }
        ]
    },
    "sn":{
        "exchangeId":"SHFE",
        "include":[
            {
                "ticker":"sn2009",
                "name":"锡2009"
            },
            {
                "ticker":"sn2010",
                "name":"锡2010"
            },
            {
                "ticker":"sn2011",
                "name":"锡2011"
            },
            {
                "ticker":"sn2012",
                "name":"锡2012"
            },
            {
                "ticker":"sn2101",
                "name":"锡2101"
            },
            {
                "ticker":"sn2102",
                "name":"锡2102"
            },
            {
                "ticker":"sn2103",
                "name":"锡2103"
            },
            {
                "ticker":"sn2104",
                "name":"锡2104"
            },
            {
                "ticker":"sn2105",
                "name":"锡2105"
            },
            {
                "ticker":"sn2106",
                "name":"锡2106"
            },
            {
                "ticker":"sn2107",
                "name":"锡2107"
            }
        ]
    },
    "SM":{
        "exchangeId":"CZCE",
        "include":[
            {
                "ticker":"SM010",
                "name":"锰硅010"
            },
            {
                "ticker":"SM011",
                "name":"锰硅011"
            },
            {
                "ticker":"SM012",
                "name":"锰硅012"
            },
            {
                "ticker":"SM101",
                "name":"锰硅101"
            },
            {
                "ticker":"SM102",
                "name":"锰硅102"
            },
            {
                "ticker":"SM103",
                "name":"锰硅103"
            },
            {
                "ticker":"SM104",
                "name":"锰硅104"
            },
            {
                "ticker":"SM105",
                "name":"锰硅105"
            }
        ]
    },
    "v":{
        "exchangeId":"DCE",
        "include":[
            {
                "ticker":"v2010",
                "name":"聚氯乙烯2010"
            },
            {
                "ticker":"v2011",
                "name":"聚氯乙烯2011"
            },
            {
                "ticker":"v2012",
                "name":"聚氯乙烯2012"
            },
            {
                "ticker":"v2101",
                "name":"聚氯乙烯2101"
            },
            {
                "ticker":"v2102",
                "name":"聚氯乙烯2102"
            },
            {
                "ticker":"v2103",
                "name":"聚氯乙烯2103"
            },
            {
                "ticker":"v2104",
                "name":"聚氯乙烯2104"
            },
            {
                "ticker":"v2105",
                "name":"聚氯乙烯2105"
            }
        ]
    },
    "y":{
        "exchangeId":"DCE",
        "include":[
            {
                "ticker":"y2011",
                "name":"豆油2011"
            },
            {
                "ticker":"y2012",
                "name":"豆油2012"
            },
            {
                "ticker":"y2101",
                "name":"豆油2101"
            },
            {
                "ticker":"y2103",
                "name":"豆油2103"
            },
            {
                "ticker":"y2105",
                "name":"豆油2105"
            },
            {
                "ticker":"y2107",
                "name":"豆油2107"
            },
            {
                "ticker":"y2108",
                "name":"豆油2108"
            }
        ]
    },
    "SA":{
        "exchangeId":"CZCE",
        "include":[
            {
                "ticker":"SA011",
                "name":"纯碱011"
            },
            {
                "ticker":"SA010",
                "name":"纯碱010"
            },
            {
                "ticker":"SA012",
                "name":"纯碱012"
            },
            {
                "ticker":"SA101",
                "name":"纯碱101"
            },
            {
                "ticker":"SA102",
                "name":"纯碱102"
            },
            {
                "ticker":"SA103",
                "name":"纯碱103"
            },
            {
                "ticker":"SA104",
                "name":"纯碱104"
            },
            {
                "ticker":"SA105",
                "name":"纯碱105"
            },
            {
                "ticker":"SA106",
                "name":"纯碱106"
            },
            {
                "ticker":"SA107",
                "name":"纯碱107"
            },
            {
                "ticker":"SA108",
                "name":"纯碱108"
            }
        ]
    },
    "TA":{
        "exchangeId":"CZCE",
        "include":[
            {
                "ticker":"TA010",
                "name":"精对苯二甲酸010"
            },
            {
                "ticker":"TA011",
                "name":"精对苯二甲酸011"
            },
            {
                "ticker":"TA012",
                "name":"精对苯二甲酸012"
            },
            {
                "ticker":"TA101",
                "name":"精对苯二甲酸101"
            },
            {
                "ticker":"TA102",
                "name":"精对苯二甲酸102"
            },
            {
                "ticker":"TA103",
                "name":"精对苯二甲酸103"
            },
            {
                "ticker":"TA104",
                "name":"精对苯二甲酸104"
            },
            {
                "ticker":"TA105",
                "name":"精对苯二甲酸105"
            },
            {
                "ticker":"TA106",
                "name":"精对苯二甲酸106"
            },
            {
                "ticker":"TA107",
                "name":"精对苯二甲酸107"
            },
            {
                "ticker":"TA108",
                "name":"精对苯二甲酸108"
            }
        ]
    },
    "SF":{
        "exchangeId":"CZCE",
        "include":[
            {
                "ticker":"SF010",
                "name":"硅铁010"
            },
            {
                "ticker":"SF011",
                "name":"硅铁011"
            },
            {
                "ticker":"SF012",
                "name":"硅铁012"
            },
            {
                "ticker":"SF101",
                "name":"硅铁101"
            },
            {
                "ticker":"SF102",
                "name":"硅铁102"
            },
            {
                "ticker":"SF103",
                "name":"硅铁103"
            },
            {
                "ticker":"SF105",
                "name":"硅铁105"
            }
        ]
    },
    "T":{
        "exchangeId":"CFFEX",
        "include":[
            {
                "ticker":"T2012",
                "name":"10年期国债2012"
            },
            {
                "ticker":"T2103",
                "name":"10年期国债2103"
            },
            {
                "ticker":"T2106",
                "name":"10年期国债2106"
            }
        ]
    }
}