{
    "log": {
        "key": "log",
        "name": "日志",
        "config": [
            {
                "key": "level",
                "name": "级别",
                "tip": "对系统内所有日志级别的设置",
                "type": "select",
                "data": [
                    { "value": "-l trace", "name": "TRACE" },
                    { "value": "-l debug", "name": "DEBUG" },
                    { "value": "-l info", "name": "INFO" },
                    { "value": "-l warning", "name": "WARN" },
                    { "value":"-l error", "name": "ERROR" },
                    { "value":"-l critical", "name": "CRITICAL" }
                ]
            }
        ]
    },

    "code": {
        "key": "code",
        "name": "编辑器",
        "config": [
            {
                "key": "tabSpaceType",
                "name": "缩进类别",
                "tip": "kungfu 编辑器缩进类别",
                "type": "select",
                "data": [
                    {"value": "Spaces", "name": "Spaces"},
                    {"value": "Tabs", "name": "Tabs"}
                ]
            },
            {
                "key": "tabSpaceSize",
                "name": "缩进大小",
                "tip": "kungfu 编辑器缩进大小（空格）",
                "type": "select",
                "data": [
                    {"value": 2, "name": 2},
                    {"value": 4, "name": 4}
                ]
            }
        ]
    }
}
